{"frames":{"img_glow":{"offX":2,"y":121,"offY":2,"h":60,"w":60,"x":955},"img_Hu":{"offX":1,"y":264,"offY":1,"h":125,"w":137,"x":0},"img_majiangpai":{"offX":0,"y":266,"offY":0,"h":114,"w":78,"x":544},"img_gangshangpao":{"offX":14,"y":130,"offY":8,"h":132,"w":336,"x":0},"img_Gang":{"offX":1,"y":254,"offY":1,"h":127,"w":137,"x":705},"img_chi":{"offX":1,"y":264,"offY":1,"h":124,"w":137,"x":139},"img_Star":{"offX":3,"y":382,"offY":3,"h":95,"w":96,"x":544},"img_yipaoduoxiang":{"offX":1,"y":0,"offY":6,"h":128,"w":367,"x":0},"img_gangshanghua":{"offX":0,"y":0,"offY":0,"h":133,"w":346,"x":369},"img_Dianpao":{"offX":1,"y":121,"offY":4,"h":131,"w":236,"x":717},"img_Ting":{"offX":1,"y":254,"offY":1,"h":126,"w":137,"x":844},"img_ZiMo":{"offX":2,"y":135,"offY":5,"h":128,"w":226,"x":338},"img_gangkai_02":{"offX":1,"y":265,"offY":7,"h":126,"w":125,"x":417},"img_Peng":{"offX":1,"y":265,"offY":1,"h":124,"w":137,"x":278},"img_haidilao":{"offX":5,"y":0,"offY":4,"h":119,"w":279,"x":717},"img_gangkai_01":{"offX":3,"y":135,"offY":5,"h":129,"w":137,"x":566}},"file":"eff.png"}